ptwordfinder/__init__.py
ptwordfinder/main.py
ptwordfinder/commands/__init__.py
ptwordfinder/commands/pt_word_finder.py
PTWordFinder-1.2.9.dist-info/LICENSE
PTWordFinder-1.2.9.dist-info/METADATA
PTWordFinder-1.2.9.dist-info/WHEEL
PTWordFinder-1.2.9.dist-info/entry_points.txt
PTWordFinder-1.2.9.dist-info/top_level.txt
PTWordFinder-1.2.9.dist-info/RECORD
