Metadata-Version: 2.1
Name: PTWordFinder
Version: 1.2.9
Summary: A command line tool that help to find specific words from a file  in any selected file.
Author: DarekRepos
License: MIT License
Requires-Python: >=3.10.6
License-File: LICENSE
Requires-Dist: click >=8.1.3
Requires-Dist: attrs >=22.1.0
Requires-Dist: exceptiongroup >=1.0.4
Requires-Dist: iniconfig >=1.1.1
Requires-Dist: packaging >=21.3
Requires-Dist: pluggy >=1.0.0
Requires-Dist: pyparsing >=2.4.2
Requires-Dist: tomli >=2.0.1
